{
  "parent": "block/block",
  "textures": {
    "chips": "agescrafting:block/wood_chips_pile",
    "particle": "agescrafting:block/wood_chips_pile"
  },
  "elements": [
    {
      "from": [0, 0, 0],
      "to": [16, 2, 16],
      "faces": {
        "north": { "uv": [0, 0, 16, 16], "texture": "#chips" },
        "east": { "uv": [0, 0, 16, 16], "texture": "#chips" },
        "south": { "uv": [0, 0, 16, 16], "texture": "#chips" },
        "west": { "uv": [0, 0, 16, 16], "texture": "#chips" },
        "up": { "uv": [0, 0, 16, 16], "texture": "#chips" },
        "down": { "uv": [0, 0, 16, 16], "texture": "#chips" }
      }
    }
  ]
}
